app/__init__.py
app/calculate_coco_features.py
app/caption.py
app/classification.py
app/dataset_browser.py
app/image_text_match.py
app/main.py
app/multimodal_search.py
app/multipage.py
app/text_localization.py
app/utils.py
app/vqa.py
docs/conf.py
lavis/__init__.py
lavis/common/config.py
lavis/common/dist_utils.py
lavis/common/gradcam.py
lavis/common/logger.py
lavis/common/optims.py
lavis/common/registry.py
lavis/common/utils.py
lavis/common/annotator/util.py
lavis/common/annotator/canny/__init__.py
lavis/common/annotator/hed/__init__.py
lavis/common/annotator/midas/__init__.py
lavis/common/annotator/midas/api.py
lavis/common/annotator/midas/utils.py
lavis/common/annotator/midas/midas/__init__.py
lavis/common/annotator/midas/midas/base_model.py
lavis/common/annotator/midas/midas/blocks.py
lavis/common/annotator/midas/midas/dpt_depth.py
lavis/common/annotator/midas/midas/midas_net.py
lavis/common/annotator/midas/midas/midas_net_custom.py
lavis/common/annotator/midas/midas/transforms.py
lavis/common/annotator/midas/midas/vit.py
lavis/common/annotator/mlsd/__init__.py
lavis/common/annotator/mlsd/utils.py
lavis/common/annotator/mlsd/models/mbv2_mlsd_large.py
lavis/common/annotator/mlsd/models/mbv2_mlsd_tiny.py
lavis/common/annotator/openpose/__init__.py
lavis/common/annotator/openpose/body.py
lavis/common/annotator/openpose/hand.py
lavis/common/annotator/openpose/model.py
lavis/common/annotator/openpose/util.py
lavis/common/annotator/uniformer/__init__.py
lavis/common/annotator/uniformer/configs/_base_/default_runtime.py
lavis/common/annotator/uniformer/configs/_base_/datasets/ade20k.py
lavis/common/annotator/uniformer/configs/_base_/datasets/chase_db1.py
lavis/common/annotator/uniformer/configs/_base_/datasets/cityscapes.py
lavis/common/annotator/uniformer/configs/_base_/datasets/cityscapes_769x769.py
lavis/common/annotator/uniformer/configs/_base_/datasets/drive.py
lavis/common/annotator/uniformer/configs/_base_/datasets/hrf.py
ammico_lavis-1.0.2.3.dist-info/LICENSE.txt
ammico_lavis-1.0.2.3.dist-info/METADATA
ammico_lavis-1.0.2.3.dist-info/WHEEL
ammico_lavis-1.0.2.3.dist-info/top_level.txt
ammico_lavis-1.0.2.3.dist-info/RECORD
